__init__.py
opentty.py
opentty-1.6.3.dist-info/LICENSE
opentty-1.6.3.dist-info/METADATA
opentty-1.6.3.dist-info/WHEEL
opentty-1.6.3.dist-info/top_level.txt
opentty-1.6.3.dist-info/RECORD
