Metadata-Version: 2.1
Name: opentty
Version: 1.6.3
Summary: The OpenTTY is a Terminal Emulator created tottaly in python based-on Unix-Like Shells
Home-page: https://github.com/fetuber4095/OpenTTY
Author: Mr. Lima
Author-email: felipebr4095@gmail.com
License: UNKNOWN
Keywords: python package,emulator,windows,linux,shell,project,posix,unix
Platform: UNKNOWN
Classifier: License :: OSI Approved :: MIT License
Classifier: Programming Language :: Python :: 3
Classifier: Programming Language :: Python :: 3.8
Classifier: Programming Language :: Python :: 3.9
Classifier: Programming Language :: Python :: 3.11
License-File: LICENSE
